[{"Term / Date": "webscraping", "Nov 6, 2022": "71", "Nov 13, 2022": "78", "Nov 20, 2022": "82", "Nov 27, 2022": "80", "Dec 4, 2022": "70", "Dec 11, 2022": "76", "Dec 18, 2022": "70", "Dec 25, 2022": "53", "Jan 1, 2023": "52", "Jan 8, 2023": "92", "Jan 15, 2023": "79", "Jan 22, 2023": "99", "Jan 29, 2023": "66", "Feb 5, 2023": "91", "Feb 12, 2023": "90", "Feb 19, 2023": "99", "Feb 26, 2023": "91", "Mar 5, 2023": "91", "Mar 12, 2023": "84", "Mar 19, 2023": "71", "Mar 26, 2023": "77", "Apr 2, 2023": "98", "Apr 9, 2023": "76", "Apr 16, 2023": "89", "Apr 23, 2023": "72", "Apr 30, 2023": "69", "May 7, 2023": "94", "May 14, 2023": "63", "May 21, 2023": "70", "May 28, 2023": "88", "Jun 4, 2023": "56", "Jun 11, 2023": "65", "Jun 18, 2023": "80", "Jun 25, 2023": "84", "Jul 2, 2023": "75", "Jul 9, 2023": "86", "Jul 16, 2023": "90", "Jul 23, 2023": "84", "Jul 30, 2023": "100", "Aug 6, 2023": "72", "Aug 13, 2023": "72", "Aug 20, 2023": "78", "Aug 27, 2023": "82", "Sep 3, 2023": "83", "Sep 10, 2023": "97", "Sep 17, 2023": "79", "Sep 24, 2023": "99", "Oct 1, 2023": "97", "Oct 8, 2023": "85", "Oct 15, 2023": "87", "Oct 22, 2023": "80"}]