{
    "universal": {
        "class_": "webtap.taps.custom.universal_tap.UniversalTap"
    },
    "contact_details": {
        "config_dir": "contact_details"
    },
    "atg_petr_cermak_yellow_pages_scraper": {
        "config_dir": "atg_petr_cermak_yellow_pages_scraper"
    },
    "atg_yin_yelp_scraper": {
        "config_dir": "atg_yin_yelp_scraper"
    },
    "atg_lukaskrivka_article_extractor_smart": {
        "config_dir": "atg_lukaskrivka_article_extractor_smart"
    },
    "atg_misceres_seo_audit_tool": {
        "config_dir": "atg_misceres_seo_audit_tool"
    },
    "atg_m0uka_bulk_image_downloader": {
        "config_dir": "atg_m0uka_bulk_image_downloader"
    },
    "atg_maxcopell_zillow_detail_scraper": {
        "config_dir": "atg_maxcopell_zillow_detail_scraper"
    },
    "atg_glenn_gif_scroll_animation": {
        "config_dir": "atg_glenn_gif_scroll_animation"
    },
    "atg_misceres_indeed_scraper": {
        "config_dir": "atg_misceres_indeed_scraper"
    },
    "atg_jupri_g2_explorer": {
        "config_dir": "atg_jupri_g2_explorer"
    },
    "atg_zuzka_covid_my": {
        "config_dir": "atg_zuzka_covid_my"
    },
    "atg_jancurn_screenshot_taker": {
        "config_dir": "atg_jancurn_screenshot_taker"
    },
    "atg_zuzka_covid_wm": {
        "config_dir": "atg_zuzka_covid_wm"
    },
    "atg_jancurn_analyze_domains": {
        "config_dir": "atg_jancurn_analyze_domains"
    },
    "atg_valek_josef_weather_scraper": {
        "config_dir": "atg_valek_josef_weather_scraper"
    },
    "atg_jancurn_find_broken_links": {
        "config_dir": "atg_jancurn_find_broken_links"
    },
    "atg_vbartonicek_topuniversities_scraper": {
        "config_dir": "atg_vbartonicek_topuniversities_scraper"
    },
    "atg_qbie_kickstarter_scraper": {
        "config_dir": "atg_qbie_kickstarter_scraper"
    },
    "atg_lhotanok_ticketmaster_scraper": {
        "config_dir": "atg_lhotanok_ticketmaster_scraper"
    },
    "atg_lukaskrivka_keywords_extractor": {
        "config_dir": "atg_lukaskrivka_keywords_extractor"
    },
    "atg_jupri_tesco_grocery": {
        "config_dir": "atg_jupri_tesco_grocery"
    },
    "atg_mhamas_website_backup": {
        "config_dir": "atg_mhamas_website_backup"
    },
    "atg_svpetrenko_quora_scraper": {
        "config_dir": "atg_svpetrenko_quora_scraper"
    },
    "atg_jupri_shopify_scraper": {
        "config_dir": "atg_jupri_shopify_scraper"
    },
    "atg_alexey_pinterest_crawler": {
        "config_dir": "atg_alexey_pinterest_crawler"
    },
    "atg_epctex_gutenberg_scraper": {
      "config_dir": "atg_epctex_gutenberg_scraper"
    },
    "atg_jupri_asda_scraper": {
        "config_dir": "atg_jupri_asda_scraper"
    },
    "atg_vaclavrut_sitemap_sniffer": {
        "config_dir": "atg_vaclavrut_sitemap_sniffer"
    },
    "atg_mtrunkat_xmls_to_dataset": {
        "config_dir": "atg_mtrunkat_xmls_to_dataset"
    },
    "atg_pocesar_json_ld_schema": {
        "config_dir": "atg_pocesar_json_ld_schema"
    },
    "atg_mvolfik_expedia_hotels_com_reviews_scraper": {
        "config_dir": "atg_mvolfik_expedia_hotels_com_reviews_scraper"
    },
    "atg_lukaskrivka_website_checker_puppeteer": {
        "config_dir": "atg_lukaskrivka_website_checker_puppeteer"
    },
    "atg_voyager_booking_reviews_scraper": {
        "config_dir": "atg_voyager_booking_reviews_scraper"
    },
    "atg_epctex_edx_scraper": {
        "config_dir": "atg_epctex_edx_scraper"
    },
    "atg_glosterr_soccerstats_scraper": {
        "config_dir": "atg_glosterr_soccerstats_scraper"
    },
    "atg_alexey_bestbuy_products_actor": {
        "config_dir": "atg_alexey_bestbuy_products_actor"
    },
    "atg_junglee_amazon_bestsellers": {
        "config_dir": "atg_junglee_amazon_bestsellers"
    },
    "atg_natasha_lekh_vegan_places_finder": {
        "config_dir": "atg_natasha_lekh_vegan_places_finder"
    },
    "atg_ivanvs_remoteok_job_scraper": {
        "config_dir": "atg_ivanvs_remoteok_job_scraper"
    },
    "atg_voyager_booking_scraper": {
        "config_dir": "atg_voyager_booking_scraper"
    },
    "atg_danielmilevski9_telegram_channel_scraper": {
        "config_dir": "atg_danielmilevski9_telegram_channel_scraper"
    },
    "atg_jupri_wordpress_scraper": {
        "config_dir": "atg_jupri_wordpress_scraper"
    },
    "atg_glosterr_whoscored_player_information_scraper": {
        "config_dir": "atg_glosterr_whoscored_player_information_scraper"
    },
    "atg_forward_dinosaur_shopify_app_store_scraper": {
        "config_dir": "atg_forward_dinosaur_shopify_app_store_scraper"
    }
}